<?xml version="1.0" encoding="UTF-8"?>
<text text-cts="urn:cts:greekLit:tlg0013.tlg019.perseus-grc2" file-name="" author="" title="Hymn 19 to Pan Machine readable text" date-of-conversion="2017-03-08">
  <t p="1" n="1" a="[1]">ἀμφί</t>
  <t p="1" n="2" a="[1]">μοι</t>
  <t p="1" n="3" a="[1]">Ἑρμείαο</t>
  <t p="1" n="4" a="[1]">φίλον</t>
  <t p="1" n="5" a="[1]">γόνον</t>
  <t p="1" n="6" a="[1]">ἔννεπε</t>
  <t p="1" n="7" a="[1]" join="b">,</t>
  <t p="1" n="8" a="[1]">Μοῦσα</t>
  <t p="1" n="9" a="[2]" join="b">,</t>
  <t p="5" n="1" a="[1]">Πᾶν᾽</t>
  <t p="5" n="2" a="[1]">ἀνακεκλόμεναι</t>
  <t p="5" n="3" a="[1]" join="b">,</t>
  <t p="5" n="4" a="[1]">νόμιον</t>
  <t p="5" n="5" a="[1]">θεόν</t>
  <t p="5" n="6" a="[2]" join="b">,</t>
  <t p="5" n="7" a="[1]">ἀγλαέθειρον</t>
  <t p="5" n="8" a="[3]" join="b">,</t>
  <t p="10" n="1" a="[1]">ἄλλοτε</t>
  <t p="10" n="2" a="[1]">δ᾽</t>
  <t p="10" n="3" a="[1]">αὖ</t>
  <t p="10" n="4" a="[1]">πέτρῃσιν</t>
  <t p="10" n="5" a="[1]">ἐν</t>
  <t p="10" n="6" a="[1]">ἠλιβάτοισι</t>
  <t p="10" n="7" a="[1]">διοιχνεῖ</t>
  <t p="10" n="8" a="[1]" join="b">,</t>
  <t p="15" n="1" a="[1]">ἄγρης</t>
  <t p="15" n="2" a="[1]">ἐξανιών</t>
  <t p="15" n="3" a="[1]" join="b">,</t>
  <t p="15" n="4" a="[1]">δονάκων</t>
  <t p="15" n="5" a="[1]">ὕπο</t>
  <t p="15" n="6" a="[1]">μοῦσαν</t>
  <t p="15" n="7" a="[1]">ἀθύρων</t>
  <t p="20" n="1" a="[1]">φοιτῶσαι</t>
  <t p="20" n="2" a="[1]">πύκα</t>
  <t p="20" n="3" a="[1]">ποσσὶν</t>
  <t p="20" n="4" a="[1]">ἐπὶ</t>
  <t p="20" n="5" a="[1]">κρήνῃ</t>
  <t p="20" n="6" a="[1]">μελανύδρῳ</t>
  <t p="25" n="1" a="[1]">ἐν</t>
  <t p="25" n="2" a="[1]">μαλακῷ</t>
  <t p="25" n="3" a="[1]">λειμῶνι</t>
  <t p="25" n="4" a="[1]" join="b">,</t>
  <t p="25" n="5" a="[1]">τόθι</t>
  <t p="25" n="6" a="[1]">κρόκος</t>
  <t p="25" n="7" a="[1]">ἠδ᾽</t>
  <t p="25" n="8" a="[1]">ὑάκινθος</t>
  <t p="30" n="1" a="[1]">καί</t>
  <t p="30" n="2" a="[1]">ῥ᾽</t>
  <t p="30" n="3" a="[1]">ὅ</t>
  <t p="30" n="4" a="[1]">γ᾽</t>
  <t p="30" n="5" a="[1]">ἐς</t>
  <t p="30" n="6" a="[1]">Ἀρκαδίην</t>
  <t p="30" n="7" a="[1]">πολυπίδακα</t>
  <t p="30" n="8" a="[1]" join="b">,</t>
  <t p="30" n="9" a="[1]">μητέρα</t>
  <t p="30" n="10" a="[1]">μήλων</t>
  <t p="30" n="11" a="[2]" join="b">,</t>
  <t p="35" n="1" a="[1]">ἐκ</t>
  <t p="35" n="2" a="[1]">δ᾽</t>
  <t p="35" n="3" a="[1]">ἐτέλεσσε</t>
  <t p="35" n="4" a="[1]">γάμον</t>
  <t p="35" n="5" a="[1]">θαλερόν</t>
  <t p="35" n="6" a="[1]" join="b">.</t>
  <t p="35" n="7" a="[1]">τέκε</t>
  <t p="35" n="8" a="[2]">δ᾽</t>
  <t p="35" n="9" a="[1]">ἐν</t>
  <t p="35" n="10" a="[1]">μεγάροισιν</t>
  <t p="40" n="1" a="[1]">τὸν</t>
  <t p="40" n="2" a="[1]">δ᾽</t>
  <t p="40" n="3" a="[1]">αἶψ᾽</t>
  <t p="40" n="4" a="[1]">Ἑρμείας</t>
  <t p="40" n="5" a="[1]">ἐριούνιος</t>
  <t p="40" n="6" a="[1]">εἰς</t>
  <t p="40" n="7" a="[1]">χέρα</t>
  <t p="40" n="8" a="[1]">θῆκε</t>
  <t p="45" n="1" a="[1]">δεῖξε</t>
  <t p="45" n="2" a="[1]">δὲ</t>
  <t p="45" n="3" a="[1]">κοῦρον</t>
  <t p="45" n="4" a="[1]">ἑόν</t>
  <t p="45" n="5" a="[1]" join="b">:</t>
  <t p="45" n="6" a="[1]">πάντες</t>
  <t p="45" n="7" a="[1]">δ᾽</t>
  <t p="45" n="8" a="[1]">ἄρα</t>
  <t p="45" n="9" a="[1]">θυμὸν</t>
  <t p="45" n="10" a="[1]">ἔτερφθεν</t>
</text>